{
  "content": "I need paint.",
  "language": "eng",
  "translations": [
    "ita:A me serve della pittura",
    "ita:A me serve della tinta",
    "ita:A me serve della vernice",
    "ita:Ho bisogno di pittura",
    "ita:Ho bisogno di tinta",
    "ita:Ho bisogno di vernice",
    "ita:Io ho bisogno di pittura",
    "ita:Io ho bisogno di tinta",
    "ita:Io ho bisogno di vernice",
    "ita:Mi serve della pittura",
    "ita:Mi serve della tinta",
    "ita:Mi serve della vernice"
  ],
  "tags": [
    "eng:tatoeba-sentence"
  ],
  "credits": [
    "Sentence from Tatoeba by Joseph (CC-BY 2.0 FR)"
  ]
}
