{
  "content": "Don't buy me anything.",
  "language": "eng",
  "translations": [
    "ita:Non comprarmi niente",
    "ita:Non comprarmi nulla",
    "ita:Non compratemi niente",
    "ita:Non compratemi nulla",
    "ita:Non mi comprare niente",
    "ita:Non mi comprare nulla",
    "ita:Non mi comprate niente",
    "ita:Non mi comprate nulla",
    "ita:Non mi compri niente",
    "ita:Non mi compri nulla"
  ],
  "tags": [
    "eng:tatoeba-sentence"
  ],
  "credits": [
    "Sentence from Tatoeba by CH (CC-BY 2.0 FR)"
  ]
}
