{
  "content": "ตาม",
  "language": "tha",
  "tags": [
    "eng:tatoeba-sentence-part"
  ],
  "relationships": [
    [
      "USAGE_EXAMPLE",
      "tha:ถ้าคุณไม่ประพฤติตามซานต้าก็จะไม่มา"
    ],
    [
      "TRANSLATION",
      "eng:according to"
    ],
    [
      "TRANSLATION",
      "eng:follow"
    ],
    [
      "TRANSLATION",
      "eng:to follow"
    ],
    [
      "TRANSLATION",
      "eng:as per"
    ],
    [
      "TRANSLATION",
      "deu:Wie gewünscht"
    ],
    [
      "TRANSLATION",
      "fra:Suivre"
    ],
    [
      "TRANSLATION",
      "ita:Seguire"
    ],
    [
      "TRANSLATION",
      "rus:Следуйте инструкциям"
    ],
    [
      "TRANSLATION",
      "tur:İzlemek"
    ]
  ],
  "logs": {
    "2026-03-28T15:23:17.755667Z": "TRANSLATION_DONE:eng",
    "2026-03-29T14:29:49.971731Z": "TRANSLATION_DONE:deu",
    "2026-03-29T14:29:50.140430Z": "TRANSLATION_DONE:fra",
    "2026-03-29T14:29:50.318700Z": "TRANSLATION_DONE:ita",
    "2026-03-29T14:29:50.495357Z": "TRANSLATION_DONE:rus",
    "2026-03-29T14:29:50.686185Z": "TRANSLATION_DONE:tur"
  },
  "transcriptions": {
    "RTGS": "tam"
  }
}
