{
  "content": "Моята майка ми направи една много симпатична пола.",
  "language": "bul",
  "tags": [
    "eng:tatoeba-sentence"
  ],
  "credits": [
    "Sentence from Tatoeba by korobo4ka (CC-BY 2.0 FR)"
  ],
  "relationships": [
    [
      "TRANSLATION",
      "eng:My mother made me a cute skirt"
    ],
    [
      "PART",
      "bul:Моята"
    ],
    [
      "PART",
      "bul:майка"
    ],
    [
      "PART",
      "bul:ми"
    ],
    [
      "PART",
      "bul:направи"
    ],
    [
      "PART",
      "bul:една"
    ],
    [
      "PART",
      "bul:много"
    ],
    [
      "PART",
      "bul:симпатична"
    ],
    [
      "PART",
      "bul:пола"
    ]
  ],
  "logs": {
    "2026-04-01T08:56:37.131638Z": "SPLIT_DONE"
  }
}
