{
  "content": "Напоследък гледал ли си някакви филми?",
  "language": "bul",
  "tags": [
    "eng:tatoeba-sentence"
  ],
  "credits": [
    "Sentence from Tatoeba by ednorog (CC-BY 2.0 FR)"
  ],
  "relationships": [
    [
      "PART",
      "bul:Напоследък"
    ],
    [
      "PART",
      "bul:гледал"
    ],
    [
      "PART",
      "bul:ли"
    ],
    [
      "PART",
      "bul:си"
    ],
    [
      "PART",
      "bul:някакви"
    ],
    [
      "PART",
      "bul:филми"
    ]
  ],
  "logs": {
    "2026-03-31T11:02:05.821479Z": "SPLIT_DONE"
  }
}
