{
  "content": "Трябва да си разчистя сметките с Том.",
  "language": "bul",
  "tags": [
    "eng:tatoeba-sentence"
  ],
  "credits": [
    "Sentence from Tatoeba by korobo4ka (CC-BY 2.0 FR)"
  ],
  "relationships": [
    [
      "PART",
      "bul:Трябва"
    ],
    [
      "PART",
      "bul:да"
    ],
    [
      "PART",
      "bul:си"
    ],
    [
      "PART",
      "bul:разчистя"
    ],
    [
      "PART",
      "bul:сметките"
    ],
    [
      "PART",
      "bul:с"
    ],
    [
      "PART",
      "bul:Том"
    ]
  ],
  "logs": {
    "2026-03-31T11:13:02.771015Z": "SPLIT_DONE"
  }
}
