{
  "content": "Jeg vet ikke hvorfor Tom gjør det.",
  "language": "nob",
  "tags": [
    "eng:tatoeba-sentence"
  ],
  "credits": [
    "Sentence from Tatoeba by Mayk (CC-BY 2.0 FR)"
  ],
  "relationships": [
    [
      "TRANSLATION",
      "eng:I don't know why Tom does that"
    ],
    [
      "PART",
      "nob:Jeg"
    ],
    [
      "PART",
      "nob:vet"
    ],
    [
      "PART",
      "nob:ikke"
    ],
    [
      "PART",
      "nob:hvorfor"
    ],
    [
      "PART",
      "nob:Tom"
    ],
    [
      "PART",
      "nob:gjør"
    ],
    [
      "PART",
      "nob:det"
    ]
  ],
  "logs": {
    "2026-04-01T08:43:52.219407Z": "SPLIT_DONE"
  }
}
