{
  "content": "المصري زَهِقَ مِن كُلّ حَاجَة في بَلَدِه",
  "language": "arz",
  "transcriptions": {
    "arabizi": "ilmasri zihi' min kullahaega fi balad|uh"
  },
  "tags": [
    "eng:lisaanmasry-sentence"
  ],
  "credits": [
    "Data from [lisaanmasry](https://eu.lisaanmasry.org/info/en/copyright.html); This material is Copyright © 2007-2020 Mike Green."
  ],
  "logs": {},
  "relationships": [
    [
      "PART",
      "arz:اِلمَصري"
    ],
    [
      "PART",
      "arz:زِهِق مِن"
    ],
    [
      "PART",
      "arz:كُلّ حاَجَة"
    ],
    [
      "PART",
      "arz:في"
    ],
    [
      "PART",
      "arz:بَلَد"
    ],
    [
      "PART",
      "arz:ُه"
    ],
    [
      "TRANSLATION",
      "eng:the egyptian gets bored with everything in his country"
    ]
  ]
}
