{
  "content": "اِلعَدّاَد شَغاَل عَلى طول مِش بِيوقَف",
  "language": "arz",
  "transcriptions": {
    "arabizi": "ilAaddaed shaghael Aala tool mish biyoo'af"
  },
  "tags": [
    "eng:lisaanmasry-sentence"
  ],
  "credits": [
    "Data from [lisaanmasry](https://eu.lisaanmasry.org/info/en/copyright.html); This material is Copyright © 2007-2020 Mike Green."
  ],
  "logs": {},
  "relationships": [
    [
      "PART",
      "arz:اِلعَدّاَد"
    ],
    [
      "PART",
      "arz:شَغاَل"
    ],
    [
      "PART",
      "arz:عَلى"
    ],
    [
      "PART",
      "arz:طول"
    ],
    [
      "PART",
      "arz:مِش"
    ],
    [
      "PART",
      "arz:بِيوقَف"
    ],
    [
      "TRANSLATION",
      "eng:the meter is working constantly, not stopping"
    ]
  ]
}
