{
  "content": "حَتّى",
  "language": "arz",
  "transcriptions": {
    "arabizi": "hatta"
  },
  "tags": [
    "eng:lisaanmasry-word"
  ],
  "credits": [
    "Data from [lisaanmasry](https://eu.lisaanmasry.org/info/en/copyright.html); This material is Copyright © 2007-2020 Mike Green."
  ],
  "logs": {},
  "relationships": [
    [
      "USAGE_EXAMPLE",
      "arz:حَتّى اِلمَدرَب مَاشَا اِلناَدي اِلنَهاَردَه"
    ],
    [
      "USAGE_EXAMPLE",
      "arz:لاَزِم تِستَيقِظ باكِراً حَتّى تَصِل في مُوعِدِكَ"
    ],
    [
      "USAGE_EXAMPLE",
      "arz:حَتّى لَو خِسِرت كِتير لاَزِم تَحاوِل ثانٍ"
    ],
    [
      "TRANSLATION",
      "eng:even"
    ],
    [
      "TRANSLATION",
      "eng:arrive"
    ],
    [
      "TRANSLATION",
      "eng:reach"
    ]
  ]
}
