{
  "content": "ولا",
  "language": "arz",
  "tags": [
    "eng:tatoeba-sentence-part",
    "eng:lisaanmasry-word"
  ],
  "usage_examples": [
    "arz:من زمان أوي والناس مبهورة بقدرته الفظيعة إنه يحل مسائل الرياضة في دماغه من غير ورقة ولا قلم",
    "arz:عصفور في الإيد و لا عشرة عالشجرة",
    "arz:أنا مـِش مـُهتـَمـَة إذا هـِي عا رِفـَة و لا لا ء",
    "arz:عاوز تاكل سمك ولا فراخ؟",
    "arz:اتصل بالمحل وشوفوا فاتح ولا لا",
    "arz:إنتِ عايزة كشري بعدس ولا من غير"
  ],
  "translations": [
    "eng:nor",
    "eng:and not",
    "eng:neither",
    "eng:not even",
    "eng:or",
    "eng:or not",
    "eng:else",
    "eng:otherwise"
  ],
  "logs": {
    "2026-01-03T08:22:33.280211Z": "TRANSLATION_DONE:eng"
  },
  "credits": [
    "Data from [lisaanmasry](https://eu.lisaanmasry.org/info/en/copyright.html); This material is Copyright © 2007-2020 Mike Green."
  ],
  "transcriptions": {
    "arabizi": "walla"
  }
}