{
  "content": "cela",
  "language": "fra",
  "relationships": [
    [
      "TRANSLATION",
      "rus:это"
    ],
    [
      "TRANSLATION",
      "tur:onu"
    ],
    [
      "TRANSLATION",
      "tur:bunu"
    ],
    [
      "TRANSLATION",
      "ita:quello"
    ],
    [
      "USAGE_EXAMPLE",
      "fra:Cela fait-il longtemps que tu travailles là-bas ﹖"
    ],
    [
      "TRANSLATION",
      "eng:that"
    ],
    [
      "TRANSLATION",
      "eng:it"
    ],
    [
      "USAGE_EXAMPLE",
      "fra:Je n'arrive pas à croire que vous ayez fait cela toutes seules"
    ],
    [
      "USAGE_EXAMPLE",
      "fra:Tout le monde sait que Tom ne peut pas faire cela"
    ],
    [
      "USAGE_EXAMPLE",
      "fra:Cela fait-il longtemps que vous travaillez là-bas ﹖"
    ],
    [
      "TRANSLATION",
      "deu:das"
    ],
    [
      "TRANSLATION",
      "deu:dies"
    ],
    [
      "USAGE_EXAMPLE",
      "fra:Combien de personnes savent-elles faire cela ﹖"
    ],
    [
      "USAGE_EXAMPLE",
      "fra:Ne nous inquiétons pas de cela maintenant"
    ],
    [
      "USAGE_EXAMPLE",
      "fra:Je ne sais pas pourquoi cela s'est produit"
    ],
    [
      "USAGE_EXAMPLE",
      "fra:Sami, de toute évidence n'avait pas entendu cela"
    ],
    [
      "USAGE_EXAMPLE",
      "fra:Vous savez que je ne pourrais pas faire cela"
    ],
    [
      "USAGE_EXAMPLE",
      "fra:Je ne devrais vraiment pas faire cela"
    ],
    [
      "USAGE_EXAMPLE",
      "fra:Mais comment peuvent-elles faire cela ﹖"
    ],
    [
      "USAGE_EXAMPLE",
      "fra:Faisons comme si nous n'avions pas entendu cela !"
    ],
    [
      "USAGE_EXAMPLE",
      "fra:Je pense que cela ne coûterait pas beaucoup"
    ],
    [
      "USAGE_EXAMPLE",
      "fra:Je ne suis pas totalement convaincu de cela"
    ],
    [
      "USAGE_EXAMPLE",
      "fra:Veuillez faire quelque chose à cela, je vous prie"
    ],
    [
      "USAGE_EXAMPLE",
      "fra:Je ne fais pas cela, normalement"
    ],
    [
      "USAGE_EXAMPLE",
      "fra:Je pensais que nous avions déjà fait cela"
    ],
    [
      "USAGE_EXAMPLE",
      "fra:Je ne peux pas expliquer pourquoi cela est arrivé"
    ],
    [
      "USAGE_EXAMPLE",
      "fra:Certains hommes ne savent pas cela"
    ],
    [
      "USAGE_EXAMPLE",
      "fra:Les gens ne veulent pas que cela se termine"
    ],
    [
      "USAGE_EXAMPLE",
      "fra:Je n'étais pas vraiment certaine de cela"
    ],
    [
      "USAGE_EXAMPLE",
      "fra:Qu'est-ce que vous faites de cela ﹖"
    ],
    [
      "USAGE_EXAMPLE",
      "fra:Dites-lui que je ne ferai pas cela !"
    ],
    [
      "USAGE_EXAMPLE",
      "fra:Je ne sais pas comment cela fonctionne"
    ],
    [
      "USAGE_EXAMPLE",
      "fra:Ils ne risqueront pas de faire cela"
    ],
    [
      "USAGE_EXAMPLE",
      "fra:Faire cela ne sera probablement pas difficile"
    ],
    [
      "USAGE_EXAMPLE",
      "fra:Je suis contente que nous n'ayons pas fait cela"
    ],
    [
      "USAGE_EXAMPLE",
      "fra:Ne dites à personne que nous avons fait cela"
    ],
    [
      "USAGE_EXAMPLE",
      "fra:Ne vous ennuyez pas à faire cela maintenant"
    ],
    [
      "USAGE_EXAMPLE",
      "fra:Ne dites à personne que nous faisons cela"
    ],
    [
      "USAGE_EXAMPLE",
      "fra:Pensez-vous vraiment que cela soit nécessaire ﹖"
    ],
    [
      "USAGE_EXAMPLE",
      "fra:Il se pourrait que cela ne soit pas si facile"
    ],
    [
      "USAGE_EXAMPLE",
      "fra:Tout cela appartient au passé maintenant"
    ],
    [
      "USAGE_EXAMPLE",
      "fra:C'est pour cela que j'ai fait tout ça"
    ],
    [
      "USAGE_EXAMPLE",
      "fra:Je savais que vous ne feriez pas cela"
    ],
    [
      "USAGE_EXAMPLE",
      "fra:Espérons que cela ne prendra pas beaucoup de temps"
    ],
    [
      "USAGE_EXAMPLE",
      "fra:Ce n'est pas comme cela qu'elle fonctionne"
    ],
    [
      "USAGE_EXAMPLE",
      "fra:Je crains que ce ne soit pas si facile que cela"
    ],
    [
      "TRANSLATION",
      "ita:ciò"
    ],
    [
      "TRANSLATION",
      "ita:questa"
    ],
    [
      "TRANSLATION",
      "ita:questo"
    ],
    [
      "TRANSLATION",
      "spa:esa"
    ],
    [
      "TRANSLATION",
      "spa:eso"
    ],
    [
      "TRANSLATION",
      "spa:esto"
    ],
    [
      "TRANSLATION",
      "spa:lo"
    ],
    [
      "TRANSLATION",
      "tat:бул"
    ],
    [
      "TRANSLATION",
      "tur:bu"
    ],
    [
      "TRANSLATION",
      "tur:bunun"
    ],
    [
      "USAGE_EXAMPLE",
      "fra:À quelle heure cela s'est-il produit ﹖"
    ],
    [
      "USAGE_EXAMPLE",
      "fra:Comment quiconque pourrait ne pas apprécier cela ﹖"
    ],
    [
      "USAGE_EXAMPLE",
      "fra:En quelque sorte, je ne peux juste pas accepter cela"
    ],
    [
      "USAGE_EXAMPLE",
      "fra:Peut-être que cela ne s'est jamais produit"
    ],
    [
      "USAGE_EXAMPLE",
      "fra:J'espère que cela peut aider quelqu'un"
    ],
    [
      "USAGE_EXAMPLE",
      "fra:Peut-être qu'un jour, tu comprendras cela"
    ],
    [
      "USAGE_EXAMPLE",
      "fra:Tout cela n'était qu'un malentendu"
    ],
    [
      "USAGE_EXAMPLE",
      "fra:Peut-être que je n'aurais pas dû faire cela"
    ],
    [
      "USAGE_EXAMPLE",
      "fra:J'aimerais vraiment que vous n'ayez pas vu cela"
    ],
    [
      "USAGE_EXAMPLE",
      "fra:J'aimerais vraiment que vous vous n'ayez pas vu cela"
    ],
    [
      "USAGE_EXAMPLE",
      "fra:J'aimerais vraiment que vous n'ayez pas fait cela"
    ],
    [
      "USAGE_EXAMPLE",
      "fra:On peut faire mieux que cela !"
    ],
    [
      "USAGE_EXAMPLE",
      "fra:Je n'arrive pas à croire que vous ayez vraiment fait cela"
    ]
  ],
  "tags": [
    "eng:tatoeba-sentence-part"
  ],
  "logs": {
    "2026-03-28T15:41:17.067687Z": "TRANSLATION_DONE:eng",
    "2026-03-28T16:44:57.566453Z": "TRANSLATION_DONE:deu"
  }
}
