{
  "content": "Des poires sont mises en boîte dans cette usine.",
  "language": "fra",
  "tags": [
    "eng:tatoeba-sentence"
  ],
  "credits": [
    "Sentence from Tatoeba by sacredceltic (CC-BY 2.0 FR)"
  ],
  "relationships": [
    [
      "PART",
      "fra:Des"
    ],
    [
      "PART",
      "fra:poires"
    ],
    [
      "PART",
      "fra:sont"
    ],
    [
      "PART",
      "fra:mises"
    ],
    [
      "PART",
      "fra:en"
    ],
    [
      "PART",
      "fra:boîte"
    ],
    [
      "PART",
      "fra:dans"
    ],
    [
      "PART",
      "fra:cette"
    ],
    [
      "PART",
      "fra:usine"
    ]
  ],
  "logs": {
    "2026-03-29T12:52:21.438505Z": "SPLIT_DONE"
  }
}
