{
  "content": "Malheureusement, ce n'est pas une option.",
  "language": "fra",
  "tags": [
    "eng:tatoeba-sentence"
  ],
  "credits": [
    "Sentence from Tatoeba by lbdx (CC-BY 2.0 FR)"
  ],
  "relationships": [
    [
      "PART",
      "fra:Malheureusement"
    ],
    [
      "PART",
      "fra:ce"
    ],
    [
      "PART",
      "fra:n'est"
    ],
    [
      "PART",
      "fra:pas"
    ],
    [
      "PART",
      "fra:une"
    ],
    [
      "PART",
      "fra:option"
    ]
  ],
  "logs": {
    "2026-03-29T12:54:05.960849Z": "SPLIT_DONE"
  }
}
