{
  "content": "also",
  "language": "eng",
  "transcriptions": {},
  "logs": {
    "2025-12-12T13:52:07.920726Z": "SPLIT_CONSIDERED_UNNECESSARY"
  },
  "morphologically_related": [],
  "parts": [],
  "has_similar_meaning": [],
  "sounds_similar": [],
  "usage_examples": [],
  "to_be_differentiated_from": [],
  "collocations": [],
  "typical_follow_up": [],
  "children": [],
  "translations": [
    "deu:auch",
    "arb:ون",
    "fin:ja",
    "apc:و",
    "spa:también",
    "arz:أيضاًَ",
    "arz:برضو",
    "arz:بَردو",
    "deu:also",
    "fra:aussi",
    "tur:Ayrıca",
    "arz:كمان"
  ],
  "notes": [],
  "tags": [
    "eng:lisaanmasry-word-translation"
  ],
  "needsHumanCheck": false,
  "excludeFromLearning": false,
  "decorativeImages": [],
  "semanticImages": [],
  "unambigiousImages": [],
  "credits": [
    "Data from [lisaanmasry](https://eu.lisaanmasry.org/info/en/copyright.html); This material is Copyright © 2007-2020 Mike Green."
  ]
}