{
  "content": "Are you naked?",
  "language": "eng",
  "tags": [
    "eng:tatoeba-sentence"
  ],
  "credits": [
    "Sentence from Tatoeba by CK (CC-BY 2.0 FR)"
  ],
  "relationships": [
    [
      "TRANSLATION",
      "ita:Sei nuda﹖"
    ],
    [
      "TRANSLATION",
      "ita:Sei nudo﹖"
    ],
    [
      "TRANSLATION",
      "ita:Siete nude﹖"
    ],
    [
      "TRANSLATION",
      "ita:Siete nudi﹖"
    ],
    [
      "TRANSLATION",
      "ita:È nuda﹖"
    ],
    [
      "TRANSLATION",
      "ita:È nudo﹖"
    ]
  ]
}
