{
  "content": "Are you the new secretary?",
  "language": "eng",
  "tags": [
    "eng:tatoeba-sentence"
  ],
  "credits": [
    "Sentence from Tatoeba by CK (CC-BY 2.0 FR)"
  ],
  "relationships": [
    [
      "TRANSLATION",
      "ita:Lei è il nuovo segretario﹖"
    ],
    [
      "TRANSLATION",
      "ita:Lei è la nuova segretaria﹖"
    ],
    [
      "TRANSLATION",
      "ita:Sei il nuovo segretario﹖"
    ],
    [
      "TRANSLATION",
      "ita:Sei la nuova segretaria﹖"
    ],
    [
      "TRANSLATION",
      "ita:Tu sei il nuovo segretario﹖"
    ],
    [
      "TRANSLATION",
      "ita:Tu sei la nuova segretaria﹖"
    ],
    [
      "TRANSLATION",
      "ita:È il nuovo segretario﹖"
    ],
    [
      "TRANSLATION",
      "ita:È la nuova segretaria﹖"
    ]
  ]
}
