{
  "content": "Don't underestimate him.",
  "language": "eng",
  "tags": [
    "eng:tatoeba-sentence"
  ],
  "credits": [
    "Sentence from Tatoeba by CH (CC-BY 2.0 FR)"
  ],
  "relationships": [
    [
      "TRANSLATION",
      "ita:Non lo sottovalutare"
    ],
    [
      "TRANSLATION",
      "ita:Non lo sottovalutate"
    ],
    [
      "TRANSLATION",
      "ita:Non lo sottovaluti"
    ],
    [
      "TRANSLATION",
      "ita:Non sottovalutarlo"
    ],
    [
      "TRANSLATION",
      "ita:Non sottovalutatelo"
    ]
  ]
}
