{
  "content": "How many people do you expect to be at your party?",
  "language": "eng",
  "tags": [
    "eng:tatoeba-sentence"
  ],
  "credits": [
    "Sentence from Tatoeba by CK (CC-BY 2.0 FR)"
  ],
  "relationships": [
    [
      "TRANSLATION",
      "ita:Quante persone si aspetta che siano alla sua festa﹖"
    ],
    [
      "TRANSLATION",
      "ita:Quante persone ti aspetti che siano alla tua festa﹖"
    ],
    [
      "TRANSLATION",
      "ita:Quante persone vi aspettate che siano alla vostra festa﹖"
    ]
  ]
}
