{
  "content": "I am annoyed by your egotism.",
  "language": "eng",
  "translations": [
    "ita:Io sono infastidita dal suo egoismo",
    "ita:Io sono infastidito dal suo egoismo",
    "ita:Sono infastidita dal suo egoismo",
    "ita:Sono infastidita dal tuo egoismo",
    "ita:Sono infastidita dal vostro egoismo",
    "ita:Sono infastidito dal suo egoismo",
    "ita:Sono infastidito dal tuo egoismo",
    "ita:Sono infastidito dal vostro egoismo"
  ],
  "tags": [
    "eng:tatoeba-sentence"
  ],
  "credits": [
    "Sentence from Tatoeba by gloeb (CC-BY 2.0 FR)"
  ]
}
