{
  "content": "I have the feeling that I've met that guy before.",
  "language": "eng",
  "tags": [
    "eng:tatoeba-sentence"
  ],
  "credits": [
    "Sentence from Tatoeba by CK (CC-BY 2.0 FR)"
  ],
  "relationships": [
    [
      "TRANSLATION",
      "ita:Ho la sensazione di avere già incontrato quel tipo"
    ],
    [
      "TRANSLATION",
      "ita:Ho la sensazione di avere già incontrato quel tizio"
    ],
    [
      "TRANSLATION",
      "ita:Io ho la sensazione di avere già incontrato quel tipo"
    ],
    [
      "TRANSLATION",
      "ita:Io ho la sensazione di avere già incontrato quel tizio"
    ]
  ]
}
