{
  "content": "I read a lot of books in English.",
  "language": "eng",
  "tags": [
    "eng:tatoeba-sentence"
  ],
  "credits": [
    "Sentence from Tatoeba by Lakeseayesno (CC-BY 2.0 FR)"
  ],
  "relationships": [
    [
      "TRANSLATION",
      "ita:Ho letto molti libri in inglese"
    ],
    [
      "TRANSLATION",
      "ita:Io ho letto molti libri in inglese"
    ],
    [
      "TRANSLATION",
      "ita:Io leggo molti libri in inglese"
    ],
    [
      "TRANSLATION",
      "ita:Io lessi molti libri in inglese"
    ],
    [
      "TRANSLATION",
      "ita:Leggo molti libri in inglese"
    ],
    [
      "TRANSLATION",
      "ita:Lessi molti libri in inglese"
    ]
  ]
}
