{
  "content": "I wanted to share it with you.",
  "language": "eng",
  "tags": [
    "eng:tatoeba-sentence"
  ],
  "credits": [
    "Sentence from Tatoeba by CK (CC-BY 2.0 FR)"
  ],
  "relationships": [
    [
      "TRANSLATION",
      "ita:La volevo condividere con lei"
    ],
    [
      "TRANSLATION",
      "ita:La volevo condividere con te"
    ],
    [
      "TRANSLATION",
      "ita:La volevo condividere con voi"
    ],
    [
      "TRANSLATION",
      "ita:Lo volevo condividere con lei"
    ],
    [
      "TRANSLATION",
      "ita:Lo volevo condividere con te"
    ],
    [
      "TRANSLATION",
      "ita:Lo volevo condividere con voi"
    ],
    [
      "TRANSLATION",
      "ita:Volevo condividerla con lei"
    ],
    [
      "TRANSLATION",
      "ita:Volevo condividerla con te"
    ],
    [
      "TRANSLATION",
      "ita:Volevo condividerla con voi"
    ],
    [
      "TRANSLATION",
      "ita:Volevo condividerlo con lei"
    ],
    [
      "TRANSLATION",
      "ita:Volevo condividerlo con te"
    ],
    [
      "TRANSLATION",
      "ita:Volevo condividerlo con voi"
    ]
  ]
}
