{
  "content": "I'm a loner.",
  "language": "eng",
  "tags": [
    "eng:tatoeba-sentence"
  ],
  "credits": [
    "Sentence from Tatoeba by CK (CC-BY 2.0 FR)"
  ],
  "relationships": [
    [
      "TRANSLATION",
      "ita:Io sono un solitario"
    ],
    [
      "TRANSLATION",
      "ita:Io sono un tipo solitario"
    ],
    [
      "TRANSLATION",
      "ita:Io sono una solitaria"
    ],
    [
      "TRANSLATION",
      "ita:Io sono una tipa solitaria"
    ],
    [
      "TRANSLATION",
      "ita:Sono un solitario"
    ],
    [
      "TRANSLATION",
      "ita:Sono un tipo solitario"
    ],
    [
      "TRANSLATION",
      "ita:Sono una solitaria"
    ],
    [
      "TRANSLATION",
      "ita:Sono una tipa solitaria"
    ]
  ]
}
