{
  "content": "I'm so hungry.",
  "language": "eng",
  "tags": [
    "eng:tatoeba-sentence"
  ],
  "credits": [
    "Sentence from Tatoeba by Scott (CC-BY 2.0 FR)"
  ],
  "relationships": [
    [
      "TRANSLATION",
      "ita:Ho così fame"
    ],
    [
      "TRANSLATION",
      "ita:Io ho così fame"
    ],
    [
      "TRANSLATION",
      "ita:Io sono così affamata"
    ],
    [
      "TRANSLATION",
      "ita:Io sono così affamato"
    ],
    [
      "TRANSLATION",
      "ita:Sono così affamata"
    ],
    [
      "TRANSLATION",
      "ita:Sono così affamato"
    ]
  ]
}
