{
  "content": "I'm proud that my father is a good cook.",
  "language": "eng",
  "tags": [
    "eng:tatoeba-sentence"
  ],
  "credits": [
    "Sentence from Tatoeba by Shoyren (CC-BY 2.0 FR)"
  ],
  "relationships": [
    [
      "TRANSLATION",
      "ita:Sono fiera che mio padre sia un bravo cuoco"
    ],
    [
      "TRANSLATION",
      "ita:Sono fiero che mio padre sia un bravo cuoco"
    ],
    [
      "TRANSLATION",
      "ita:Sono orgogliosa che mio padre sia un bravo cuoco"
    ],
    [
      "TRANSLATION",
      "ita:Sono orgoglioso che mio padre sia un bravo cuoco"
    ]
  ]
}
