{
  "content": "I'm trying to stay awake.",
  "language": "eng",
  "translations": [
    "ita:Sto cercando di restare sveglia",
    "ita:Sto cercando di restare sveglio",
    "ita:Sto cercando di rimanere sveglia",
    "ita:Sto cercando di rimanere sveglio",
    "ita:Sto provando a restare sveglia",
    "ita:Sto provando a restare sveglio",
    "ita:Sto provando a rimanere sveglia",
    "ita:Sto provando a rimanere sveglio"
  ],
  "tags": [
    "eng:tatoeba-sentence"
  ],
  "credits": [
    "Sentence from Tatoeba by CK (CC-BY 2.0 FR)"
  ]
}
