{
  "content": "OK.",
  "language": "eng",
  "tags": [
    "eng:tatoeba-sentence",
    "eng:lisaanmasry-word-translation",
    "eng:tatoeba-sentence-part"
  ],
  "credits": [
    "Sentence from Tatoeba by Eldad (CC-BY 2.0 FR)",
    "Data from [lisaanmasry](https://eu.lisaanmasry.org/info/en/copyright.html); This material is Copyright © 2007-2020 Mike Green."
  ],
  "logs": {
    "2026-04-01T08:35:30.802414Z": "TRANSLATION_DONE:ukr",
    "2026-04-01T09:04:17.515383Z": "TRANSLATION_DONE:kor"
  },
  "relationships": [
    [
      "TRANSLATION",
      "ita:OK"
    ],
    [
      "TRANSLATION",
      "arz:ماَشي؟"
    ],
    [
      "USAGE_EXAMPLE",
      "eng:Is it OK if I open a can﹖"
    ],
    [
      "TRANSLATION",
      "ukr:ЦІНА",
      "Auto-translated with argostranslate (en→uk)"
    ],
    [
      "USAGE_EXAMPLE",
      "eng:Would it be OK if I turned off the lights﹖"
    ],
    [
      "TRANSLATION",
      "kor:알겠습니다",
      "Auto-translated with translategemma:4b"
    ]
  ]
}
