{
  "content": "Please buy this for me.",
  "language": "eng",
  "tags": [
    "eng:tatoeba-sentence"
  ],
  "credits": [
    "Sentence from Tatoeba by CK (CC-BY 2.0 FR)"
  ],
  "relationships": [
    [
      "TRANSLATION",
      "ita:Per favore, compra questo per me"
    ],
    [
      "TRANSLATION",
      "ita:Per favore, comprate questo per me"
    ],
    [
      "TRANSLATION",
      "ita:Per favore, compri questo per me"
    ],
    [
      "TRANSLATION",
      "ita:Per piacere, compra questo per me"
    ],
    [
      "TRANSLATION",
      "ita:Per piacere, comprate questo per me"
    ],
    [
      "TRANSLATION",
      "ita:Per piacere, compri questo per me"
    ]
  ]
}
