{
  "content": "She shrieked.",
  "language": "eng",
  "tags": [
    "eng:tatoeba-sentence"
  ],
  "credits": [
    "Sentence from Tatoeba by Spamster (CC-BY 2.0 FR)"
  ],
  "relationships": [
    [
      "TRANSLATION",
      "ita:Gridò"
    ],
    [
      "TRANSLATION",
      "ita:Ha gridato"
    ],
    [
      "TRANSLATION",
      "ita:Ha strillato"
    ],
    [
      "TRANSLATION",
      "ita:Ha urlato"
    ],
    [
      "TRANSLATION",
      "ita:Lei gridò"
    ],
    [
      "TRANSLATION",
      "ita:Lei ha gridato"
    ],
    [
      "TRANSLATION",
      "ita:Lei ha strillato"
    ],
    [
      "TRANSLATION",
      "ita:Lei ha urlato"
    ],
    [
      "TRANSLATION",
      "ita:Lei strillò"
    ],
    [
      "TRANSLATION",
      "ita:Lei urlò"
    ],
    [
      "TRANSLATION",
      "ita:Strillò"
    ],
    [
      "TRANSLATION",
      "ita:Urlò"
    ]
  ]
}
