{
  "content": "We should be millionaires.",
  "language": "eng",
  "tags": [
    "eng:tatoeba-sentence"
  ],
  "credits": [
    "Sentence from Tatoeba by CM (CC-BY 2.0 FR)"
  ],
  "relationships": [
    [
      "TRANSLATION",
      "ita:Dovremmo essere milionari"
    ],
    [
      "TRANSLATION",
      "ita:Dovremmo essere milionarie"
    ],
    [
      "TRANSLATION",
      "ita:Noi dovremmo essere milionari"
    ],
    [
      "TRANSLATION",
      "ita:Noi dovremmo essere milionarie"
    ]
  ]
}
