{
  "content": "year",
  "language": "eng",
  "tags": [
    "eng:lisaanmasry-word-translation"
  ],
  "credits": [
    "Data from [lisaanmasry](https://eu.lisaanmasry.org/info/en/copyright.html); This material is Copyright © 2007-2020 Mike Green."
  ],
  "logs": {},
  "relationships": [
    [
      "TRANSLATION",
      "ita:anno"
    ],
    [
      "TRANSLATION",
      "tur:yıl"
    ],
    [
      "TRANSLATION",
      "apc:سنة"
    ],
    [
      "TRANSLATION",
      "arz:سِنِينَ"
    ],
    [
      "TRANSLATION",
      "arz:السنة"
    ],
    [
      "TRANSLATION",
      "arz:في"
    ],
    [
      "TRANSLATION",
      "arz:اِلسَنَة"
    ],
    [
      "TRANSLATION",
      "arz:سنتين"
    ],
    [
      "TRANSLATION",
      "arz:اَلسَّنَةِ"
    ],
    [
      "TRANSLATION",
      "arz:سَنَة"
    ],
    [
      "TRANSLATION",
      "arz:سِنين"
    ],
    [
      "TRANSLATION",
      "deu:Jahr"
    ],
    [
      "TRANSLATION",
      "arz:سنين"
    ],
    [
      "TRANSLATION",
      "arz:سَنَتين"
    ],
    [
      "TRANSLATION",
      "arz:السَّنَة"
    ],
    [
      "TRANSLATION",
      "bul:година"
    ],
    [
      "TRANSLATION",
      "ben:বছর"
    ],
    [
      "TRANSLATION",
      "fra:année"
    ]
  ]
}
