{
  "content": "You should come.",
  "language": "eng",
  "tags": [
    "eng:tatoeba-sentence"
  ],
  "credits": [
    "Sentence from Tatoeba by CK (CC-BY 2.0 FR)"
  ],
  "relationships": [
    [
      "TRANSLATION",
      "ita:Dovrebbe venire"
    ],
    [
      "TRANSLATION",
      "ita:Dovreste venire"
    ],
    [
      "TRANSLATION",
      "ita:Dovresti venire"
    ],
    [
      "TRANSLATION",
      "ita:Lei dovrebbe venire"
    ],
    [
      "TRANSLATION",
      "ita:Tu dovresti venire"
    ],
    [
      "TRANSLATION",
      "ita:Voi dovreste venire"
    ]
  ]
}
