{
  "content": "You seem very happy.",
  "language": "eng",
  "tags": [
    "eng:tatoeba-sentence"
  ],
  "credits": [
    "Sentence from Tatoeba by CK (CC-BY 2.0 FR)"
  ],
  "relationships": [
    [
      "TRANSLATION",
      "ita:Lei sembra molto felice"
    ],
    [
      "TRANSLATION",
      "ita:Sembra molto felice"
    ],
    [
      "TRANSLATION",
      "ita:Sembrate molto felici"
    ],
    [
      "TRANSLATION",
      "ita:Sembri molto felice"
    ],
    [
      "TRANSLATION",
      "ita:Tu sembri molto felice"
    ],
    [
      "TRANSLATION",
      "ita:Voi sembrate molto felici"
    ]
  ]
}
