{
  "content": "トムがメアリーのこと嫌いだって、本当なの？",
  "language": "jpn",
  "tags": [
    "eng:tatoeba-sentence"
  ],
  "credits": [
    "Sentence from Tatoeba by bunbuku (CC-BY 2.0 FR)"
  ],
  "relationships": [
    [
      "TRANSLATION",
      "eng:Is it true Tom doesn't like Mary﹖"
    ],
    [
      "PART",
      "jpn:トム"
    ],
    [
      "PART",
      "jpn:が"
    ],
    [
      "PART",
      "jpn:メアリー"
    ],
    [
      "PART",
      "jpn:の"
    ],
    [
      "PART",
      "jpn:こと"
    ],
    [
      "PART",
      "jpn:嫌い"
    ],
    [
      "PART",
      "jpn:だ"
    ],
    [
      "PART",
      "jpn:って"
    ],
    [
      "PART",
      "jpn:本当"
    ],
    [
      "PART",
      "jpn:な"
    ]
  ],
  "logs": {
    "2026-04-01T08:44:40.667776Z": "SPLIT_DONE"
  }
}
