{
  "content": "フランス",
  "language": "jpn",
  "tags": [
    "eng:tatoeba-sentence-part"
  ],
  "relationships": [
    [
      "USAGE_EXAMPLE",
      "jpn:フランス語を身に付けるのは簡単ですか？"
    ],
    [
      "USAGE_EXAMPLE",
      "jpn:フランス語を習得するのは大変ですか？"
    ],
    [
      "USAGE_EXAMPLE",
      "jpn:フランス語を覚えるのは、早かったですよ。"
    ],
    [
      "USAGE_EXAMPLE",
      "jpn:だれかがあなたにフランス語を教えているのですか。"
    ],
    [
      "TRANSLATION",
      "eng:France",
      "Auto-translated with argostranslate (ja→en)"
    ],
    [
      "USAGE_EXAMPLE",
      "jpn:トムはフランス語をかなり上手に話すことができる。"
    ],
    [
      "USAGE_EXAMPLE",
      "jpn:トムはね、メアリーにフランス語を勉強してほしいと思ってるんだ。"
    ],
    [
      "USAGE_EXAMPLE",
      "jpn:すみません。私、フランス語が分からないんです。"
    ],
    [
      "USAGE_EXAMPLE",
      "jpn:もしかしたら、トムはフランス語がわからないんじゃないかな。"
    ]
  ],
  "logs": {
    "2026-03-31T12:50:38.592885Z": "TRANSLATION_DONE:eng"
  }
}
