{
  "content": "嘘をつかれるのは嫌だよね。",
  "language": "jpn",
  "tags": [
    "eng:tatoeba-sentence"
  ],
  "credits": [
    "Sentence from Tatoeba by small_snow (CC-BY 2.0 FR)"
  ],
  "relationships": [
    [
      "PART",
      "jpn:嘘"
    ],
    [
      "PART",
      "jpn:を"
    ],
    [
      "PART",
      "jpn:つかれる"
    ],
    [
      "PART",
      "jpn:の"
    ],
    [
      "PART",
      "jpn:は"
    ],
    [
      "PART",
      "jpn:嫌"
    ],
    [
      "PART",
      "jpn:だ"
    ],
    [
      "PART",
      "jpn:よ"
    ],
    [
      "PART",
      "jpn:ね"
    ],
    [
      "PART",
      "jpn:。"
    ]
  ],
  "logs": {
    "2026-03-31T11:17:19.085500Z": "SPLIT_DONE"
  }
}
