{
  "content": "Dieses Medikament könnte zu seiner Genesung beitragen.",
  "language": "deu",
  "tags": [
    "eng:tatoeba-sentence"
  ],
  "credits": [
    "Sentence from Tatoeba by Tamy (CC-BY 2.0 FR)"
  ],
  "relationships": [
    [
      "PART",
      "deu:Dieses"
    ],
    [
      "PART",
      "deu:Medikament"
    ],
    [
      "PART",
      "deu:könnte"
    ],
    [
      "PART",
      "deu:zu"
    ],
    [
      "PART",
      "deu:seiner"
    ],
    [
      "PART",
      "deu:Genesung"
    ],
    [
      "PART",
      "deu:beitragen"
    ]
  ],
  "logs": {
    "2026-03-31T11:09:54.783149Z": "SPLIT_DONE"
  }
}
