{
  "content": "fragen",
  "language": "deu",
  "transcriptions": {},
  "logs": {
    "2025-12-12T14:08:36.244902Z": "SPLIT_CONSIDERED_UNNECESSARY",
    "2025-12-12T14:20:36.910374Z": "USAGE_EXAMPLE_CONSIDERED_IMPOSSIBLE:deu",
    "2026-03-29T13:18:51.434802Z": "TRANSLATION_DONE:fra",
    "2026-03-29T13:18:51.595321Z": "TRANSLATION_DONE:ita",
    "2026-03-29T13:18:51.745281Z": "TRANSLATION_DONE:rus",
    "2026-03-29T13:18:51.920033Z": "TRANSLATION_DONE:tur",
    "2026-03-31T11:37:24.166321Z": "TRANSLATION_DONE:ukr",
    "2026-03-31T11:37:24.313790Z": "TRANSLATION_DONE:kor"
  },
  "tags": [
    "eng:tatoeba-sentence-part"
  ],
  "relationships": [
    [
      "USAGE_EXAMPLE",
      "deu:Ich werde nicht fragen, warum du das willst"
    ],
    [
      "TRANSLATION",
      "eng:ask"
    ],
    [
      "TRANSLATION",
      "ces:ptáte"
    ],
    [
      "TRANSLATION",
      "fra:questions"
    ],
    [
      "TRANSLATION",
      "ita:domande"
    ],
    [
      "TRANSLATION",
      "rus:вопросы"
    ],
    [
      "TRANSLATION",
      "tur:sorular"
    ],
    [
      "TRANSLATION",
      "ita:chiedere"
    ],
    [
      "USAGE_EXAMPLE",
      "deu:Sollen wir diesen einen Mechaniker fragen﹖"
    ],
    [
      "TRANSLATION",
      "ukr:Про нас",
      "Auto-translated with argostranslate (de→en→uk)"
    ],
    [
      "TRANSLATION",
      "kor:이름",
      "Auto-translated with argostranslate (de→en→ko)"
    ],
    [
      "USAGE_EXAMPLE",
      "deu:Du solltest besser deinen Arzt fragen"
    ]
  ]
}
