{
  "content": "Faccio molte cose alla volta, quindi non solo sto leggendo cose di Akutagawa, ho anche aumentato il tempo che trascorro leggendo in inglese e leggo anche un po' in tedesco ogni giorno.",
  "language": "ita",
  "translations": [
    "eng:I do many things at the same time, so not only am I reading things by Akutagawa, I've also increased the amount of time"
  ],
  "tags": [
    "eng:tatoeba-sentence"
  ],
  "credits": [
    "Sentence from Tatoeba by Guybrush88 (CC-BY 2.0 FR)"
  ]
}
