{
  "content": "Loro",
  "language": "ita",
  "tags": [
    "eng:tatoeba-sentence-part"
  ],
  "logs": {
    "2025-12-28T14:36:23.973133Z": "TRANSLATION_DONE:eng"
  },
  "relationships": [
    [
      "USAGE_EXAMPLE",
      "ita:Loro ci aiutano"
    ],
    [
      "USAGE_EXAMPLE",
      "ita:Loro stanno parlando di lei﹖"
    ],
    [
      "USAGE_EXAMPLE",
      "ita:Loro sono fratello e sorella"
    ],
    [
      "USAGE_EXAMPLE",
      "ita:Loro l'hanno fatta davvero"
    ],
    [
      "TRANSLATION",
      "eng:parrots"
    ],
    [
      "TRANSLATION",
      "eng:them"
    ],
    [
      "TRANSLATION",
      "eng:they"
    ],
    [
      "TRANSLATION",
      "eng:you all"
    ]
  ]
}
