{
  "content": "Non vediamo le cose così come sono, le vediamo così come siamo.",
  "language": "ita",
  "translations": [
    "eng:We don't see things as they are, we see them as we are"
  ],
  "tags": [
    "eng:tatoeba-sentence"
  ],
  "credits": [
    "Sentence from Tatoeba by WM3DAS (CC-BY 2.0 FR)"
  ],
  "parts": [
    "ita:Non",
    "ita:vediamo",
    "ita:le",
    "ita:cose",
    "ita:così",
    "ita:come",
    "ita:sono",
    "ita:siamo"
  ],
  "logs": {
    "2025-12-28T14:04:33.830105Z": "SPLIT_DONE"
  }
}
