{
  "content": "provare",
  "language": "ita",
  "tags": [
    "eng:tatoeba-sentence-part"
  ],
  "logs": {
    "2025-12-28T15:00:25.917713Z": "TRANSLATION_DONE:eng"
  },
  "relationships": [
    [
      "USAGE_EXAMPLE",
      "ita:Dovreste provare a vivere con le vostre capacità"
    ],
    [
      "TRANSLATION",
      "eng:to try"
    ],
    [
      "TRANSLATION",
      "eng:to test"
    ],
    [
      "TRANSLATION",
      "eng:to prove"
    ],
    [
      "TRANSLATION",
      "eng:to attempt"
    ],
    [
      "TRANSLATION",
      "deu:versuchen"
    ]
  ]
}
