{
  "content": "حتى الأطفال بإمكانهم قراءة هذا الكتاب.",
  "language": "ara",
  "tags": [
    "eng:tatoeba-sentence"
  ],
  "credits": [
    "Sentence from Tatoeba by saeb (CC-BY 2.0 FR)"
  ],
  "relationships": [
    [
      "PART",
      "ara:حتى"
    ],
    [
      "PART",
      "ara:الأطفال"
    ],
    [
      "PART",
      "ara:بإمكانهم"
    ],
    [
      "PART",
      "ara:قراءة"
    ],
    [
      "PART",
      "ara:هذا"
    ],
    [
      "PART",
      "ara:الكتاب"
    ]
  ],
  "logs": {
    "2026-03-31T11:12:29.582238Z": "SPLIT_DONE"
  }
}
