{
  "content": "كانت هناك غابة خلف ذلك المنزل.",
  "language": "ara",
  "tags": [
    "eng:tatoeba-sentence"
  ],
  "credits": [
    "Sentence from Tatoeba by dididodo (CC-BY 2.0 FR)"
  ],
  "relationships": [
    [
      "PART",
      "ara:كانت"
    ],
    [
      "PART",
      "ara:هناك"
    ],
    [
      "PART",
      "ara:غابة"
    ],
    [
      "PART",
      "ara:خلف"
    ],
    [
      "PART",
      "ara:ذلك"
    ],
    [
      "PART",
      "ara:المنزل"
    ]
  ],
  "logs": {
    "2026-03-31T11:01:43.043009Z": "SPLIT_DONE"
  }
}
