{
  "content": "Den här klockan verkar inte fungera som den ska.",
  "language": "swe",
  "tags": [
    "eng:tatoeba-sentence"
  ],
  "credits": [
    "Sentence from Tatoeba by Siljan (CC-BY 2.0 FR)"
  ],
  "relationships": [
    [
      "PART",
      "swe:Den"
    ],
    [
      "PART",
      "swe:här"
    ],
    [
      "PART",
      "swe:klockan"
    ],
    [
      "PART",
      "swe:verkar"
    ],
    [
      "PART",
      "swe:inte"
    ],
    [
      "PART",
      "swe:fungera"
    ],
    [
      "PART",
      "swe:som"
    ],
    [
      "PART",
      "swe:den"
    ],
    [
      "PART",
      "swe:ska"
    ]
  ],
  "logs": {
    "2026-03-31T13:12:15.015867Z": "SPLIT_DONE"
  }
}
