{
  "content": "hadden",
  "language": "nld",
  "tags": [
    "eng:tatoeba-sentence-part"
  ],
  "relationships": [
    [
      "USAGE_EXAMPLE",
      "nld:Waarom hadden jullie een hamer nodig﹖"
    ],
    [
      "TRANSLATION",
      "eng:had",
      "Auto-translated with argostranslate (nl→en)"
    ],
    [
      "USAGE_EXAMPLE",
      "nld:We hadden naar je moeten luisteren, Tom"
    ],
    [
      "USAGE_EXAMPLE",
      "nld:Wij hadden verwacht van Tom dat hij zich beter zou gedragen"
    ],
    [
      "USAGE_EXAMPLE",
      "nld:Ik wou dat we het allebei niet zo druk hadden"
    ]
  ],
  "logs": {
    "2026-03-31T12:50:55.408582Z": "TRANSLATION_DONE:eng"
  }
}
