{
  "content": "Tem um café na esquina.",
  "language": "por",
  "transcriptions": {},
  "logs": {},
  "tags": [],
  "needsHumanCheck": false,
  "excludeFromLearning": false,
  "decorativeImages": [],
  "semanticImages": [],
  "unambigiousImages": [],
  "relationships": [
    [
      "TRANSLATION",
      "eng:There is a café on the corner"
    ],
    [
      "TRANSLATION",
      "eng:There's a coffee shop at the corner"
    ],
    [
      "TRANSLATION",
      "eng:A café is located at the corner"
    ]
  ]
}
