{
  "content": "Из-за них Тому пришлось поменять своё мнение.",
  "language": "rus",
  "tags": [
    "eng:tatoeba-sentence"
  ],
  "credits": [
    "Sentence from Tatoeba by amanshi (CC-BY 2.0 FR)"
  ],
  "relationships": [
    [
      "PART",
      "rus:Из-за"
    ],
    [
      "PART",
      "rus:них"
    ],
    [
      "PART",
      "rus:Тому"
    ],
    [
      "PART",
      "rus:пришлось"
    ],
    [
      "PART",
      "rus:поменять"
    ],
    [
      "PART",
      "rus:своё"
    ],
    [
      "PART",
      "rus:мнение"
    ]
  ],
  "logs": {
    "2026-03-31T13:11:48.609591Z": "SPLIT_DONE"
  }
}
