{
  "content": "Тома",
  "language": "rus",
  "tags": [
    "eng:tatoeba-sentence-part"
  ],
  "relationships": [
    [
      "USAGE_EXAMPLE",
      "rus:Я уже три дня Тома не видел"
    ],
    [
      "TRANSLATION",
      "deu:Thomas"
    ],
    [
      "TRANSLATION",
      "deu:Tom"
    ],
    [
      "TRANSLATION",
      "eng:Toma"
    ],
    [
      "TRANSLATION",
      "eng:Thomas"
    ],
    [
      "TRANSLATION",
      "eng:Tommy"
    ],
    [
      "TRANSLATION",
      "fra:Tom"
    ],
    [
      "TRANSLATION",
      "fra:Thomas"
    ],
    [
      "TRANSLATION",
      "ita:Tommaso"
    ],
    [
      "TRANSLATION",
      "ita:Toma"
    ],
    [
      "TRANSLATION",
      "tur:Tom"
    ],
    [
      "TRANSLATION",
      "tur:Toma"
    ],
    [
      "TRANSLATION",
      "tur:Tom'a"
    ],
    [
      "TRANSLATION",
      "tur:Tom'un"
    ],
    [
      "USAGE_EXAMPLE",
      "rus:Мы со вчерашнего дня Тома не видели"
    ],
    [
      "USAGE_EXAMPLE",
      "rus:Мы не видели Тома со вчерашнего дня"
    ],
    [
      "USAGE_EXAMPLE",
      "rus:Будем надеяться, что мы сегодня увидим Тома"
    ],
    [
      "USAGE_EXAMPLE",
      "rus:Мы бы никогда не взяли Тома на работу"
    ],
    [
      "USAGE_EXAMPLE",
      "rus:Я ненавидел за это Тома"
    ],
    [
      "USAGE_EXAMPLE",
      "rus:Я знал, что вы не забудете Тома"
    ],
    [
      "USAGE_EXAMPLE",
      "rus:Я видел, что у Тома проблемы"
    ],
    [
      "USAGE_EXAMPLE",
      "rus:Я не думаю, что это вина Тома"
    ],
    [
      "USAGE_EXAMPLE",
      "rus:Я никогда не видел Тома таким разочарованным"
    ],
    [
      "USAGE_EXAMPLE",
      "rus:Они сказали, что никогда не видели Тома"
    ],
    [
      "USAGE_EXAMPLE",
      "rus:Попроси Тома, чтобы он мне позвонил"
    ],
    [
      "USAGE_EXAMPLE",
      "rus:Я знала, мне следовало выйти замуж за Тома"
    ],
    [
      "USAGE_EXAMPLE",
      "rus:Попросите Тома, чтобы он мне позвонил"
    ],
    [
      "USAGE_EXAMPLE",
      "rus:Позвоните мне, если найдёте Тома"
    ],
    [
      "USAGE_EXAMPLE",
      "rus:Соседи Тома позвонили в службу спасения"
    ],
    [
      "USAGE_EXAMPLE",
      "rus:Мне, наверное, надо попросить у Тома прощения"
    ],
    [
      "USAGE_EXAMPLE",
      "rus:Вы не могли бы попросить Тома, чтобы он мне позвонил﹖"
    ],
    [
      "USAGE_EXAMPLE",
      "rus:«Что-то я Тома никак не найду». — «Попробую ему позвонить»"
    ],
    [
      "USAGE_EXAMPLE",
      "rus:Ты не мог бы попросить Тома, чтобы он мне позвонил﹖"
    ],
    [
      "USAGE_EXAMPLE",
      "rus:Вы не могли бы попросить Тома позвонить мне﹖"
    ],
    [
      "USAGE_EXAMPLE",
      "rus:Я не могу найти Тома. — Попробуй позвонить ему"
    ],
    [
      "USAGE_EXAMPLE",
      "rus:Ты не мог бы попросить Тома позвонить мне﹖"
    ],
    [
      "USAGE_EXAMPLE",
      "rus:Вам надо было пригласить Тома, а вы этого не сделали"
    ],
    [
      "USAGE_EXAMPLE",
      "rus:Я знала, мне надо было выходить замуж за Тома"
    ]
  ],
  "logs": {
    "2026-03-28T15:28:46.565551Z": "TRANSLATION_DONE:deu",
    "2026-03-28T15:28:47.906495Z": "TRANSLATION_DONE:eng",
    "2026-03-28T15:28:48.710756Z": "TRANSLATION_DONE:fra",
    "2026-03-28T15:28:50.665573Z": "TRANSLATION_DONE:ita",
    "2026-03-28T15:28:52.285350Z": "TRANSLATION_DONE:tur"
  }
}
