{
  "content": "You look very tired.",
  "language": "eng",
  "translations": [
    "ita:Lei sembra molto stanca",
    "ita:Lei sembra molto stanco",
    "ita:Sembra molto stanca",
    "ita:Sembra molto stanco",
    "ita:Sembrate molto stanche",
    "ita:Sembrate molto stanchi",
    "ita:Sembri molto stanca",
    "ita:Sembri molto stanco",
    "ita:Tu sembri molto stanca",
    "ita:Tu sembri molto stanco"
  ],
  "tags": [
    "eng:tatoeba-sentence"
  ],
  "credits": [
    "Sentence from Tatoeba by CK (CC-BY 2.0 FR)"
  ]
}
