{
  "content": "Eum sine causa ex officio movere non possumus.",
  "language": "lat",
  "tags": [
    "eng:tatoeba-sentence"
  ],
  "credits": [
    "Sentence from Tatoeba by carlosalberto (CC-BY 2.0 FR)"
  ],
  "relationships": [
    [
      "PART",
      "lat:Eum"
    ],
    [
      "PART",
      "lat:sine"
    ],
    [
      "PART",
      "lat:causa"
    ],
    [
      "PART",
      "lat:ex"
    ],
    [
      "PART",
      "lat:officio"
    ],
    [
      "PART",
      "lat:movere"
    ],
    [
      "PART",
      "lat:non"
    ],
    [
      "PART",
      "lat:possumus"
    ]
  ],
  "logs": {
    "2026-03-31T13:10:44.319829Z": "SPLIT_DONE"
  }
}
