{
  "content": "Alberto yedda ad d-yegmer tiḥlawatin deg tlemmast n temdint.",
  "language": "ber",
  "tags": [
    "eng:tatoeba-sentence"
  ],
  "credits": [
    "Sentence from Tatoeba by Amastan (CC-BY 2.0 FR)"
  ],
  "relationships": [
    [
      "PART",
      "ber:Alberto"
    ],
    [
      "PART",
      "ber:yedda"
    ],
    [
      "PART",
      "ber:ad"
    ],
    [
      "PART",
      "ber:d-yegmer"
    ],
    [
      "PART",
      "ber:tiḥlawatin"
    ],
    [
      "PART",
      "ber:deg"
    ],
    [
      "PART",
      "ber:tlemmast"
    ],
    [
      "PART",
      "ber:n"
    ],
    [
      "PART",
      "ber:temdint"
    ]
  ],
  "logs": {
    "2026-03-31T11:12:54.262112Z": "SPLIT_DONE"
  }
}
