{
  "content": "Gece yarısından sonra burada hiçbir şey olmaz.",
  "language": "tur",
  "tags": [
    "eng:tatoeba-sentence"
  ],
  "credits": [
    "Sentence from Tatoeba by duran (CC-BY 2.0 FR)"
  ],
  "relationships": [
    [
      "PART",
      "tur:Gece"
    ],
    [
      "PART",
      "tur:yarısından"
    ],
    [
      "PART",
      "tur:sonra"
    ],
    [
      "PART",
      "tur:burada"
    ],
    [
      "PART",
      "tur:hiçbir"
    ],
    [
      "PART",
      "tur:şey"
    ],
    [
      "PART",
      "tur:olmaz"
    ]
  ],
  "logs": {
    "2026-03-31T13:13:15.561965Z": "SPLIT_DONE"
  }
}
