{
  "content": "她給我們看了一頂漂亮的帽子。",
  "language": "cmn",
  "tags": [
    "eng:tatoeba-sentence"
  ],
  "credits": [
    "Sentence from Tatoeba by Martha (CC-BY 2.0 FR)"
  ],
  "relationships": [
    [
      "PART",
      "cmn:她給"
    ],
    [
      "PART",
      "cmn:我們"
    ],
    [
      "PART",
      "cmn:看"
    ],
    [
      "PART",
      "cmn:了"
    ],
    [
      "PART",
      "cmn:一頂"
    ],
    [
      "PART",
      "cmn:漂亮"
    ],
    [
      "PART",
      "cmn:的"
    ],
    [
      "PART",
      "cmn:帽子"
    ],
    [
      "PART",
      "cmn:。"
    ]
  ],
  "logs": {
    "2026-03-31T11:13:21.780547Z": "SPLIT_DONE"
  }
}
