{
  "content": "pedí",
  "language": "spa",
  "tags": [
    "eng:tatoeba-sentence-part"
  ],
  "relationships": [
    [
      "USAGE_EXAMPLE",
      "spa:Le pedí al mayordomo que nos sirviese un café"
    ],
    [
      "TRANSLATION",
      "deu:Ich habe bestellt"
    ],
    [
      "TRANSLATION",
      "eng:I ordered"
    ],
    [
      "TRANSLATION",
      "fra:j'ai demandé"
    ],
    [
      "TRANSLATION",
      "ita:ho ordinato"
    ],
    [
      "TRANSLATION",
      "rus:Я заказал"
    ],
    [
      "TRANSLATION",
      "tur:emdim"
    ]
  ],
  "logs": {
    "2026-03-29T14:26:02.885554Z": "TRANSLATION_DONE:deu",
    "2026-03-29T14:26:03.082335Z": "TRANSLATION_DONE:eng",
    "2026-03-29T14:26:03.303986Z": "TRANSLATION_DONE:fra",
    "2026-03-29T14:26:03.484105Z": "TRANSLATION_DONE:ita",
    "2026-03-29T14:26:03.671004Z": "TRANSLATION_DONE:rus",
    "2026-03-29T14:26:03.867873Z": "TRANSLATION_DONE:tur"
  }
}
