{
  "content": "Are you sure you want to continue doing this?",
  "language": "eng",
  "translations": [
    "ita:Sei sicura di voler continuare a fare questo﹖",
    "ita:Sei sicura di volere continuare a fare questo﹖",
    "ita:Sei sicuro di voler continuare a fare questo﹖",
    "ita:Sei sicuro di volere continuare a fare questo﹖",
    "ita:Siete sicure di voler continuare a fare questo﹖",
    "ita:Siete sicure di volere continuare a fare questo﹖",
    "ita:Siete sicuri di voler continuare a fare questo﹖",
    "ita:Siete sicuri di volere continuare a fare questo﹖",
    "ita:È sicura di voler continuare a fare questo﹖",
    "ita:È sicura di volere continuare a fare questo﹖",
    "ita:È sicuro di voler continuare a fare questo﹖",
    "ita:È sicuro di volere continuare a fare questo﹖"
  ],
  "tags": [
    "eng:tatoeba-sentence"
  ],
  "credits": [
    "Sentence from Tatoeba by CK (CC-BY 2.0 FR)"
  ]
}
